MANIFEST.in
README.txt
setup.py
com/__init__.py
com/radware/__init__.py
com/radware/vdirect/__init__.py
com/radware/vdirect/device/__init__.py
com/radware/vdirect/device/client.py
com/radware/vdirect/device/demo.py
com/radware/vdirect/device/meta/__init__.py
com/radware/vdirect/device/meta/alteon.py
com/radware/vdirect/device/meta/appwall661.py
com/radware/vdirect/device/meta/dp6.py
com/radware/vdirect/device/meta/dp7.py
com/radware/vdirect/device/meta/dp8.py
com/radware/vdirect/device/vdirect_configuration_templates/___core__.vm
com/radware/vdirect/device/vdirect_configuration_templates/___params__.vm
com/radware/vdirect/device/vdirect_configuration_templates/__alteon_read_client__.vm
com/radware/vdirect/device/vdirect_configuration_templates/__appwall_read_client__.vm
com/radware/vdirect/device/vdirect_configuration_templates/__dp_read_client__.vm
device_client.egg-info/PKG-INFO
device_client.egg-info/SOURCES.txt
device_client.egg-info/dependency_links.txt
device_client.egg-info/requires.txt
device_client.egg-info/top_level.txt