Metadata-Version: 1.1
Name: device-client
Version: 1.0
Summary: Radware devices python client based on vDirect
Home-page: https://www.radware.com
Author: Avishay Balderman
Author-email: avishayb@radware.com
License: MIT
Platform: UNKNOWN
Classifier: Development Status :: 3 - Alpha
Classifier: Intended Audience :: Developers
Classifier: Topic :: Software Development :: Build Tools
Classifier: Programming Language :: Python :: 2
Classifier: Programming Language :: Python :: 2.6
Classifier: Programming Language :: Python :: 2.7
